weektimetable/__init__.py
weektimetable-0.0.1.dist-info/LICENSE.txt
weektimetable-0.0.1.dist-info/METADATA
weektimetable-0.0.1.dist-info/WHEEL
weektimetable-0.0.1.dist-info/top_level.txt
weektimetable-0.0.1.dist-info/RECORD
